tfs/__init__.py
tfs/tfs.py
tfsx-1.2.14.dist-info/METADATA
tfsx-1.2.14.dist-info/WHEEL
tfsx-1.2.14.dist-info/top_level.txt
tfsx-1.2.14.dist-info/RECORD
