Metadata-Version: 2.1
Name: tfsx
Version: 1.2.14
Summary: A Wrapper to access information from Microsoft DevOps
Home-page: https://gitlab.com/integration_seon/libs/application/tfs
Author: Paulo Sergio dos Santo Junior
Author-email: paulossjuniort@gmail.com
License: UNKNOWN
Platform: UNKNOWN
Classifier: Programming Language :: Python :: 3
Classifier: License :: OSI Approved :: MIT License
Classifier: Operating System :: OS Independent
Requires-Dist: azure-devops (==5.1.0b1)
Requires-Dist: requestx
